odoo/addons/l10n_es_vat_book_invoice_summary/README.rst
odoo/addons/l10n_es_vat_book_invoice_summary/__init__.py
odoo/addons/l10n_es_vat_book_invoice_summary/__manifest__.py
odoo/addons/l10n_es_vat_book_invoice_summary/i18n/es.po
odoo/addons/l10n_es_vat_book_invoice_summary/i18n/l10n_es_vat_book_invoice_summary.pot
odoo/addons/l10n_es_vat_book_invoice_summary/readme/CONTRIBUTORS.rst
odoo/addons/l10n_es_vat_book_invoice_summary/readme/DESCRIPTION.rst
odoo/addons/l10n_es_vat_book_invoice_summary/report/__init__.py
odoo/addons/l10n_es_vat_book_invoice_summary/report/vat_book_xlsx.py
odoo/addons/l10n_es_vat_book_invoice_summary/static/description/icon.png
odoo/addons/l10n_es_vat_book_invoice_summary/static/description/index.html
odoo/addons/l10n_es_vat_book_invoice_summary/tests/__init__.py
odoo/addons/l10n_es_vat_book_invoice_summary/tests/test_l10n_es_vat_book_invoice_summary.py
odoo14_addon_l10n_es_vat_book_invoice_summary-14.0.1.0.1.dev3.dist-info/METADATA
odoo14_addon_l10n_es_vat_book_invoice_summary-14.0.1.0.1.dev3.dist-info/WHEEL
odoo14_addon_l10n_es_vat_book_invoice_summary-14.0.1.0.1.dev3.dist-info/top_level.txt
odoo14_addon_l10n_es_vat_book_invoice_summary-14.0.1.0.1.dev3.dist-info/RECORD
